thordata/__init__.py
thordata/_example_utils.py
thordata/_utils.py
thordata/async_client.py
thordata/client.py
thordata/demo.py
thordata/enums.py
thordata/exceptions.py
thordata/models.py
thordata/retry.py
thordata/serp_engines.py
thordata_sdk-1.2.0.dist-info/licenses/LICENSE
thordata_sdk-1.2.0.dist-info/METADATA
thordata_sdk-1.2.0.dist-info/WHEEL
thordata_sdk-1.2.0.dist-info/top_level.txt
thordata_sdk-1.2.0.dist-info/RECORD
