Metadata-Version: 2.4
Name: thordata-sdk
Version: 1.2.0
Summary: The Official Python SDK for Thordata - AI Data Infrastructure & Proxy Network.
Author-email: Thordata Developer Team <support@thordata.com>
License: MIT
Project-URL: Homepage, https://www.thordata.com
Project-URL: Documentation, https://github.com/Thordata/thordata-python-sdk#readme
Project-URL: Source, https://github.com/Thordata/thordata-python-sdk
Project-URL: Tracker, https://github.com/Thordata/thordata-python-sdk/issues
Project-URL: Changelog, https://github.com/Thordata/thordata-python-sdk/blob/main/CHANGELOG.md
Keywords: web scraping,proxy,residential proxy,datacenter proxy,ai,llm,data-mining,serp,thordata,web scraper,anti-bot bypass
Classifier: Development Status :: 4 - Beta
Classifier: Intended Audience :: Developers
Classifier: Topic :: Software Development :: Libraries :: Python Modules
Classifier: Topic :: Internet :: WWW/HTTP
Classifier: Topic :: Internet :: Proxy Servers
Classifier: Programming Language :: Python :: 3
Classifier: Programming Language :: Python :: 3.9
Classifier: Programming Language :: Python :: 3.10
Classifier: Programming Language :: Python :: 3.11
Classifier: Programming Language :: Python :: 3.12
Classifier: License :: OSI Approved :: MIT License
Classifier: Operating System :: OS Independent
Classifier: Typing :: Typed
Requires-Python: >=3.9
License-File: LICENSE
Requires-Dist: requests>=2.25.0
Requires-Dist: aiohttp>=3.9.0
Requires-Dist: PySocks>=1.7.1
Provides-Extra: dev
Requires-Dist: pytest>=7.0.0; extra == "dev"
Requires-Dist: pytest-asyncio>=0.21.0; extra == "dev"
Requires-Dist: pytest-cov>=4.0.0; extra == "dev"
Requires-Dist: pytest-httpserver>=1.0.0; extra == "dev"
Requires-Dist: python-dotenv>=1.0.0; extra == "dev"
Requires-Dist: black>=23.0.0; extra == "dev"
Requires-Dist: ruff>=0.1.0; extra == "dev"
Requires-Dist: mypy>=1.0.0; extra == "dev"
Requires-Dist: types-requests>=2.28.0; extra == "dev"
Requires-Dist: aioresponses>=0.7.6; extra == "dev"
Dynamic: license-file
